<initial_setup>
    <hub>
        <subscription_manager>
            <server_panel>
                <server value="" />
                <proxy>
                    <proxy_server value="" />
                    <OK/>
                </proxy>
                <next />
            </server_panel>
            <user_panel>
                <username value="" />
                <password value="" />
                <next/>
            </user_panel>
            <done />
        </subscription_manager>
    </hub>
</initial_setup>
